jupyterlab_theme_winter/__init__.py
jupyterlab_theme_winter/_version.py
jupyterlab_theme_winter/labextension/package.json
jupyterlab_theme_winter/labextension/static/549.3c93e61ad0b008923486.js
jupyterlab_theme_winter/labextension/static/568.04795bd404a48828fd00.js
jupyterlab_theme_winter/labextension/static/remoteEntry.145945e9241636b2912a.js
jupyterlab_theme_winter/labextension/static/style.js
jupyterlab_theme_winter/labextension/themes/@datalayer-jupyter/jupyterlab-theme-winter/index.css
jupyterlab_theme_winter/labextension/themes/@datalayer-jupyter/jupyterlab-theme-winter/index.js
jupyterlab_theme_winter-0.1.0.data/data/share/jupyter/labextensions/@datalayer-jupyter/jupyterlab-theme-winter/install.json
jupyterlab_theme_winter-0.1.0.data/data/share/jupyter/labextensions/@datalayer-jupyter/jupyterlab-theme-winter/package.json
jupyterlab_theme_winter-0.1.0.data/data/share/jupyter/labextensions/@datalayer-jupyter/jupyterlab-theme-winter/static/549.3c93e61ad0b008923486.js
jupyterlab_theme_winter-0.1.0.data/data/share/jupyter/labextensions/@datalayer-jupyter/jupyterlab-theme-winter/static/568.04795bd404a48828fd00.js
jupyterlab_theme_winter-0.1.0.data/data/share/jupyter/labextensions/@datalayer-jupyter/jupyterlab-theme-winter/static/remoteEntry.145945e9241636b2912a.js
jupyterlab_theme_winter-0.1.0.data/data/share/jupyter/labextensions/@datalayer-jupyter/jupyterlab-theme-winter/static/style.js
jupyterlab_theme_winter-0.1.0.data/data/share/jupyter/labextensions/@datalayer-jupyter/jupyterlab-theme-winter/themes/@datalayer-jupyter/jupyterlab-theme-winter/index.css
jupyterlab_theme_winter-0.1.0.data/data/share/jupyter/labextensions/@datalayer-jupyter/jupyterlab-theme-winter/themes/@datalayer-jupyter/jupyterlab-theme-winter/index.js
jupyterlab_theme_winter-0.1.0.dist-info/LICENSE
jupyterlab_theme_winter-0.1.0.dist-info/METADATA
jupyterlab_theme_winter-0.1.0.dist-info/WHEEL
jupyterlab_theme_winter-0.1.0.dist-info/top_level.txt
jupyterlab_theme_winter-0.1.0.dist-info/RECORD
