Metadata-Version: 2.1
Name: jupyterlab-theme-winter
Version: 0.1.0
Summary: JupyterLab Theme Winter, Designed by Isabela Presedo-Floyd
Home-page: https://github.com/datalayer-jupyter/jupyterlab-theme-winter
Author: Isabela Presedo-Floyd; Eric Charles; Jovyans at Quansight
License: BSD-3-Clause
Keywords: Jupyter,JupyterLab,JupyterLab3
Platform: Linux
Platform: Mac OS X
Platform: Windows
Classifier: License :: OSI Approved :: BSD License
Classifier: Programming Language :: Python
Classifier: Programming Language :: Python :: 3
Classifier: Programming Language :: Python :: 3.6
Classifier: Programming Language :: Python :: 3.7
Classifier: Programming Language :: Python :: 3.8
Classifier: Framework :: Jupyter
Requires-Python: >=3.6
Requires-Dist: jupyterlab (==3.*,>=3.0.0rc2)
